edcon/__init__.py
edcon/cli/__init__.py
edcon/cli/cli.py
edcon/cli/gui.py
edcon/cli/parameter_set_load.py
edcon/cli/pnu.py
edcon/cli/position.py
edcon/cli/tg1.py
edcon/cli/tg102.py
edcon/cli/tg111.py
edcon/cli/tg9.py
edcon/edrive/__init__.py
edcon/edrive/com_base.py
edcon/edrive/com_ethernetip.py
edcon/edrive/com_modbus.py
edcon/edrive/diagnosis.py
edcon/edrive/motion_handler.py
edcon/edrive/parameter.py
edcon/edrive/parameter_handler.py
edcon/edrive/parameter_mapping.py
edcon/edrive/parameter_set.py
edcon/edrive/pnu_packing.py
edcon/edrive/position_telegram_handler.py
edcon/edrive/telegram102_handler.py
edcon/edrive/telegram111_handler.py
edcon/edrive/telegram1_handler.py
edcon/edrive/telegram9_handler.py
edcon/edrive/telegram_handler.py
edcon/edrive/velocity_telegram_handler.py
edcon/edrive/data/icp_map.csv
edcon/edrive/data/pnu_map.csv
edcon/gui/__init__.py
edcon/gui/connection_widget.py
edcon/gui/gui.py
edcon/gui/main_window.py
edcon/gui/motion_tab.py
edcon/gui/parameter_tab.py
edcon/gui/parameter_table_model.py
edcon/gui/processdata_model.py
edcon/gui/processdata_tab.py
edcon/gui/pyqt_helpers.py
edcon/gui/state_diagram.py
edcon/gui/state_diagram_widget.py
edcon/gui/toggle_button_model.py
edcon/gui/ui/connection.ui
edcon/gui/ui/main_window.ui
edcon/gui/ui/motion_tab.ui
edcon/gui/ui/parameter_tab.ui
edcon/gui/ui/processdata_tab.ui
edcon/gui/ui/state_diagram.ui
edcon/gui/ui/toggle_button_styles.css
edcon/profidrive/__init__.py
edcon/profidrive/telegram1.py
edcon/profidrive/telegram102.py
edcon/profidrive/telegram111.py
edcon/profidrive/telegram9.py
edcon/profidrive/telegram_base.py
edcon/profidrive/words.py
edcon/utils/__init__.py
edcon/utils/boollist.py
edcon/utils/func_helpers.py
edcon/utils/logging.py
festo_edcon-0.15.0.dist-info/licenses/LICENSE
festo_edcon-0.15.0.dist-info/METADATA
festo_edcon-0.15.0.dist-info/WHEEL
festo_edcon-0.15.0.dist-info/entry_points.txt
festo_edcon-0.15.0.dist-info/top_level.txt
festo_edcon-0.15.0.dist-info/RECORD
