Metadata-Version: 2.4
Name: festo-edcon
Version: 0.15.0
Summary: Library to issue profidrive tasks for Festo specific electrical drives
Author-email: Elias Rosch <elias.rosch@festo.com>
License: MIT
Project-URL: Documentation, https://festo-research.gitlab.io/electric-automation/festo-edcon
Project-URL: Repository, https://gitlab.com/festo-research/electric-automation/festo-edcon
Project-URL: Changelog, https://gitlab.com/festo-research/electric-automation/festo-edcon/-/blob/main/CHANGELOG.md
Classifier: Programming Language :: Python :: 3
Classifier: License :: OSI Approved :: MIT License
Classifier: Operating System :: OS Independent
Requires-Python: >=3.10
License-File: LICENSE
Requires-Dist: pymodbus==3.11.3
Requires-Dist: ethernetip==1.1.2
Requires-Dist: rich==14.2.0
Requires-Dist: setuptools==80.9.0
Requires-Dist: pytest==8.4.2
Requires-Dist: pytest-mock==3.15.1
Provides-Extra: gui
Requires-Dist: pyqt5; extra == "gui"
Dynamic: license-file
